_sciagraph_autoload.pth
sciagraph/__init__.py
sciagraph/__main__.py
sciagraph/_autoenv.py
sciagraph/_initialization.py
sciagraph/_sciagraph.cpython-311-darwin.so
sciagraph/_sciagraph_debug.cpython-311-darwin.so
sciagraph/_utils.py
sciagraph/api.py
sciagraph/licenses.html
sciagraph/store_token.py
sciagraph/integrations/__init__.py
sciagraph/integrations/_ipython.py
sciagraph/integrations/celery.py
sciagraph/integrations/mlflow.py
sciagraph/integrations/opentelemetry.py
sciagraph-2024.10.0.data/data/share/jupyter/kernels/sciagraph/kernel.json
sciagraph-2024.10.0.data/data/share/jupyter/kernels/sciagraph/logo-32x32.png
sciagraph-2024.10.0.data/data/share/jupyter/kernels/sciagraph/logo-64x64.png
sciagraph-2024.10.0.data/scripts/sciagraph-diff
sciagraph-2024.10.0.dist-info/METADATA
sciagraph-2024.10.0.dist-info/WHEEL
sciagraph-2024.10.0.dist-info/top_level.txt
sciagraph-2024.10.0.dist-info/RECORD
