Metadata-Version: 2.1
Name: sciagraph
Version: 2024.10.0
Summary: A production-speed performance and memory profiler for data batch processing applications.
Home-page: http://sciagraph.com
Maintainer: Hyphenated Enterprises LLC
Maintainer-email: itamar@pythonspeed.com
License: Proprietary
Requires-Dist: importlib-metadata; python_version < "3.8"
